bqup/__init__.py
bqup/dataset.py
bqup/main.py
bqup/project.py
bqup/routine.py
bqup/table.py
bqup-0.0.14.dist-info/LICENSE
bqup-0.0.14.dist-info/METADATA
bqup-0.0.14.dist-info/WHEEL
bqup-0.0.14.dist-info/entry_points.txt
bqup-0.0.14.dist-info/top_level.txt
bqup-0.0.14.dist-info/RECORD
