Metadata-Version: 2.1
Name: bqup
Version: 0.0.14
Summary: BigQuery backup scripts
Home-page: https://github.com/thinkingmachines/bqup
Author: Thinking Machines Data Science
Author-email: engineering@thinkingmachin.es
License: MIT License
Keywords: google bigquery,bigquery,bq,backup,bqup
Platform: UNKNOWN
Requires-Dist: docopt
Requires-Dist: google-cloud-bigquery (==2.25.1)
Requires-Dist: pytest
